doa_py/__init__.py
doa_py/arrays.py
doa_py/plot.py
doa_py/signals.py
doa_py/algorithm/__init__.py
doa_py/algorithm/broadband.py
doa_py/algorithm/esprit_based.py
doa_py/algorithm/music_based.py
doa_py/algorithm/sparse.py
doa_py/algorithm/utils.py
doa_py-1.3.1.dist-info/LICENSE
doa_py-1.3.1.dist-info/METADATA
doa_py-1.3.1.dist-info/WHEEL
doa_py-1.3.1.dist-info/top_level.txt
doa_py-1.3.1.dist-info/RECORD
