Metadata-Version: 2.1
Name: doa_py
Version: 1.3.1
Summary: DOA estimation algorithms implemented in Python
Home-page: https://github.com/zhiim/doa_py
Author: Qian Xu
Author-email: xuq3196@outlook.com
License: MIT
Classifier: Development Status :: 3 - Alpha
Classifier: Intended Audience :: Science/Research
Classifier: License :: OSI Approved :: MIT License
Classifier: Programming Language :: Python :: 3
Classifier: Programming Language :: Python :: 3.9
Classifier: Programming Language :: Python :: 3.10
Classifier: Programming Language :: Python :: 3.11
License-File: LICENSE
Requires-Dist: numpy
Requires-Dist: matplotlib
Requires-Dist: scipy
Requires-Dist: scikit-image
Requires-Dist: cvxpy
